starrail/__init__.py
starrail/config.py
starrail/version.py
starrail/entry/__init__.py
starrail/entry/cli.py
starrail/entry/gui.py
starrail/entry/setup.py
starrail/gacha/__init__.py
starrail/gacha/autodet.py
starrail/gacha/database.py
starrail/gacha/factory.py
starrail/gacha/fetch.py
starrail/gacha/fileio.py
starrail/gacha/migrate.py
starrail/gacha/parse.py
starrail/gacha/service.py
starrail/gacha/type.py
starrail/gacha/url.py
starrail/gui/__init__.py
starrail/gui/application.py
starrail/gui/common/__init__.py
starrail/gui/common/config.py
starrail/gui/common/icon.py
starrail/gui/common/stylesheet.py
starrail/gui/common/thread.py
starrail/gui/common/utils.py
starrail/gui/interfaces/__init__.py
starrail/gui/interfaces/announcements.py
starrail/gui/interfaces/base.py
starrail/gui/interfaces/gacha_sync.py
starrail/gui/interfaces/home.py
starrail/gui/interfaces/setting.py
starrail/gui/interfaces/unlock_fps.py
starrail/gui/interfaces/users.py
starrail/gui/widgets/__init__.py
starrail/gui/widgets/button.py
starrail/gui/widgets/dialog.py
starrail/gui/widgets/link_card.py
starrail/gui/widgets/pie_chart.py
starrail/gui/widgets/title_bar.py
starrail/mihoyo/__init__.py
starrail/mihoyo/api.py
starrail/mihoyo/client.py
starrail/mihoyo/dynamic_secret.py
starrail/mihoyo/qrcode.py
starrail/mihoyo/service.py
starrail/unlock/__init__.py
starrail/unlock/fps.py
starrail/unlock/service.py
starrail/utils/__init__.py
starrail/utils/accounts.py
starrail/utils/auto_update.py
starrail/utils/download.py
starrail/utils/loggings.py
starrail/utils/misc.py
starrail/utils/schedule.py
starrail/utils/security.py
starrail/utils/babelfish/__init__.py
starrail/utils/babelfish/constants.py
starrail/utils/babelfish/dictionary.py
starrail/utils/babelfish/locale.py
starrail/utils/babelfish/multilingual.py
starrail/utils/babelfish/translate.py
starrail_toolkit-0.7.5.dist-info/LICENSE
starrail_toolkit-0.7.5.dist-info/METADATA
starrail_toolkit-0.7.5.dist-info/WHEEL
starrail_toolkit-0.7.5.dist-info/entry_points.txt
starrail_toolkit-0.7.5.dist-info/top_level.txt
starrail_toolkit-0.7.5.dist-info/RECORD
