Metadata-Version: 2.1
Name: starrail-toolkit
Version: 0.7.5
Summary: Honkai Star Rail Toolkit
Home-page: https://github.com/LittleNyima/honkai-starrail-toolkit
Author: LittleNyima
Author-email: littlenyima@163.com
License: GPLv3
Classifier: Development Status :: 4 - Beta
Classifier: License :: OSI Approved :: GNU General Public License v3 (GPLv3)
Classifier: Operating System :: OS Independent
Classifier: Programming Language :: Python :: 3
License-File: LICENSE
Requires-Dist: easydict
Requires-Dist: openpyxl
Requires-Dist: pandas
Requires-Dist: prettytable
Requires-Dist: PTable
Requires-Dist: pycryptodomex
Requires-Dist: PySide6
Requires-Dist: PySide6-Fluent-Widgets
Requires-Dist: PySideSix-Frameless-Window
Requires-Dist: qrcode
Requires-Dist: requests
Requires-Dist: setuptools
